Workbook
Name ACTION: #REF!

Sheet Cover
C2: TEST CASE
B4: Project Name | C4: Counter Sales System | F4: Creator | G4: Tran Vinh Huy, Tran Bui Ty Ty
B5: Project Code | C5: CSS | F5: Reviewer/Approver | G5: Do Minh Quan, Le Thi My Huong
B6: Document Code | C6: =C5&"_"&"XXX"&"_"&"vx.x" -> CSS_XXX_vx.x | F6: Issue Date | G6: 22/10/2025
F7: Version
B10: Record of change
B11: Effective Date | C11: Version | D11: Change Item | E11: *A,D,M | F11: Change description | G11: Reference
B12: 22/10/2025 | C12: v1 | D12: Tạo mới test case Product Number & Profit Margin | E12: A | F12: Thêm 12 test case kiểm thử nhập mã sản phẩm và lợi nhuận biên | G12: Class_exercise_TH.pdf

Sheet Test case List
D1: TEST CASE LIST
B3: Project Name | D3: =Cover!C4 -> Counter Sales System
B4: Project Code | D4: =Cover!C5 -> CSS
B5: Test Environment Setup Description | D5: <List enviroment requires in this system 1. Server 2. Database 3. Web Browser ... >
B8: No | C8: Function Name | D8: Sheet Name | E8: Description | F8: Pre-Condition
B9: 1 | C9: Product Number Validation | D9: Module 1 | E9: Check the format, length, and character validity of the encrypted product | F9: The system runs, with an interface to enter the Product Number.
B10: 2 | C10: Profit Margin Calculation | D10: Module 2 | E10: Check calculation of selling price and profit (≥30%) | F10: Products with WAC available in database

Sheet Module2
A2: Module Code | B2: Module2 | J2: Pass
A3: Test requirement | B3: <Brief description about requirements which are tested in this sheet> | J3: Fail
A4: Tester
A5: Pass | B5: Fail | C5: Untested | D5: N/A | E5: Number of Test cases | J5: Untesed
A6: =COUNTIF(F9:F1000,"Pass") -> 0 | B6: =COUNTIF(F9:F1000,"Fail") -> 0 | C6: =E6-D6-B6-A6 -> 5 | D6: =COUNTIF(F$9:F$1000,"N/A") -> 0 | E6: =COUNTA(A9:A1000) -> 5 | J6: N/A
A8: ID | B8: Test Case Description | C8: Test Case Procedure | D8: Expected Output | E8: Inter-test case Dependence | F8: Result | G8: Test date | H8: Note
A9: TC_PM_01 | B9: Calculate profit margin when selling price ≥ 30% above WAC | C9: 1. Open Price Override. 2. Enter WAC = 8.25, Selling Price = 10.75. 3. Click OK. | D9: Profit Margin = ((10.75−8.25)/8.25)×100 = 30.3%. System accepts transaction. | H9: Meets minimum 30% rule.
A10: TC_PM_02 | B10: Reject sale when profit margin < 30% | C10: 1. Enter WAC = 8.25, Selling Price = 9.50. 2. Click OK. | D10: Profit Margin = ((9.50−8.25)/8.25)×100 = 15.1%. System shows warning “Profit margin below 30%” and blocks sale. | H10: Business rule enforcement.
A11: TC_PM_03 | B11: Calculate new price from entered profit margin (≥30%) | C11: 1. Select “Profit Margin %”. 2. Enter WAC = 8.25, Profit Margin = 40%. 3. Click OK. | D11: New Price = 8.25 × 1.4 = 11.55. Transaction accepted. | H11: Forward calculation.
A12: TC_PM_04 | B12: Reject invalid profit margin input (<30%) | C12: 1. Select “Profit Margin %”. 2. Enter 20%. 3. Click OK. | D12: New Price = 9.90, but system blocks sale: “Profit margin must be ≥30%”. | H12: Validation rule.
A13: TC_PM_05 | B13: Verify rounding at threshold value | C13: 1. Enter WAC = 8.25, Selling Price = 10.72. 2. Click OK. | D13: Computed margin = 29.94% → Rejected (since <30%) | H13: Edge case precision test.

Sheet Module1
A2: Module Code | B2: Module1 | J2: Pass
A3: Test requirement | B3: <Brief description about requirements which are tested in this sheet> | J3: Fail
A4: Tester
A5: Pass | B5: Fail | C5: Untested | D5: N/A | E5: Number of Test cases | J5: Untesed
A6: =COUNTIF(F9:F990,"Pass") -> 0 | B6: =COUNTIF(F9:F990,"Fail") -> 0 | C6: =E6-D6-B6-A6 -> 7 | D6: =COUNTIF(F$9:F$990,"N/A") -> 0 | E6: =COUNTA(A9:A990) -> 7 | J6: N/A
A8: ID | B8: Test Case Description | C8: Test Case Procedure | D8: Expected Output | E8: Test data | F8: Result | G8: Test data | H8: Description
A9: PN-001 | B9: Product Number field is masked to accept 10 digits only. | C9: 1. Enter product number in the field: [0123456789] | D9: Export the product that matches the specified product number. | E9: TestData01 | G9: TestData01 | H9: Show product information
A10: PN-002 | B10: Product Number field is more than 10 digits. | C10: 1. Enter product number in the field: [01234567890] | D10: Export "Product number is more than 10 digits" | E10: TestData02 | G10: TestData02 | H10: Show message: "fail in format - Product number is more than 10 digits"
A11: PN-003 | B11: Product Number field is less than 10 digits. | C11: 1. Enter product number in the field: [0123456] | D11: Export "Product number is less than 10 digits" | E11: TestData03 | G11: TestData03 | H11: Show message: "fail in format - Product number is less than 10 digits"
A12: PN-004 | B12: Product Number has character in the field | C12: 1. Enter product number in the field: [012a! 67890] | D12: Export "Product number has character" | E12: TestData04 | G12: TestData04 | H12: Show message: "fail in format - Product number include non-number"
A13: PN-005 | B13: Product number may have leading zeros. | C13: 1. Enter product number in the field: [0123456789] | D13: Export the product that matches the specified product number. | E13: TestData05 | G13: TestData05 | H13: Show product information
A14: PN-006 | B14: The product number is not found | C14: 1. Enter product number in the field: [0123456789] | D14: Show message ‘Item not found’ or similar message should be displayed to the user. | E14: TestData06 | G14: TestData06 | H14: Show message ‘Item not found’ when product number not found
A15: PN-007 | B15: If a product is taxable | C15: 1. Enter product number in the field: [0123456789] | D15: Product Number will be marked with an asterisk. [*0123456789] | E15: TestData07 | G15: TestData07 | H15: Product Number will be marked with an asterisk.

Sheet Test Report
B1: TEST REPORT
B3: Project Name | C3: <Project Name> | E3: Creator
B4: Project Code | C4: <Project Code> | E4: Reviewer/Approver
B5: Document Code | C5: =C4&"_"&"Test Report"&"_"&"vx.x" -> <Project Code>_Test Report_vx.x | E5: Issue Date | H5: <Date when this test report is created>
B6: Notes | C6: <List modules included in this release> ex: Release 1 includes 2 modules: Module1 and Module2
B10: No | C10: Module code | D10: Pass | E10: Fail | F10: Untested | G10: N/A | H10: Number of test cases
B11: 1 | C11: =Module1!B2 -> Module1 | D11: =Module1!A6 -> 0 | E11: =Module1!B6 -> 0 | F11: =Module1!C6 -> 7 | G11: =Module1!D6 -> 0 | H11: =Module1!E6 -> 7
B12: 2 | C12: =Module2!B2 -> Module2 | D12: =Module2!A6 -> 0 | E12: =Module2!B6 -> 0 | F12: =Module2!C6 -> 5 | G12: =Module2!D6 -> 0 | H12: =Module2!E6 -> 5
C14: Sub total | D14: =SUM(D9:D13) -> 0 | E14: =SUM(E9:E13) -> 0 | F14: =SUM(F9:F13) -> 12 | G14: =SUM(G9:G13) -> 0 | H14: =SUM(H9:H13) -> 12
C16: Test coverage | E16: =(D14+E14)*100/(H14-G14) -> 0 | F16: %
C17: Test successful coverage | E17: =D14*100/(H14-G14) -> 0 | F17: %
